{
  "todos": [
    {
      "title": "é isso ai",
      "completed": true,
      "id": 1
    },
    {
      "title": "Estudar Vuee",
      "completed": true,
      "id": 2
    },
    {
      "title": "Estudar composition API",
      "completed": false,
      "id": 3
    },
    {
      "title": "teste",
      "completed": true,
      "id": 4
    },
    {
      "title": "rwe",
      "completed": false,
      "id": 5
    },
    {
      "title": "aqui ó seu babaca",
      "completed": false,
      "id": 6
    },
    {
      "title": "x",
      "completed": false,
      "id": 7
    },
    {
      "title": "rwe",
      "completed": false,
      "id": 8
    },
    {
      "title": "r",
      "completed": false,
      "id": 9
    },
    {
      "title": "b",
      "completed": false,
      "id": 10
    },
    {
      "title": "rwe",
      "completed": false,
      "id": 11
    }
  ]
}